alphainsight_jc6102/__init__.py
alphainsight_jc6102/alphainsight_jc6102.py
alphainsight_jc6102-0.1.0.dist-info/LICENSE
alphainsight_jc6102-0.1.0.dist-info/METADATA
alphainsight_jc6102-0.1.0.dist-info/WHEEL
alphainsight_jc6102-0.1.0.dist-info/RECORD
